socketIO_client/__init__.py
socketIO_client/exceptions.py
socketIO_client/heartbeats.py
socketIO_client/logs.py
socketIO_client/namespaces.py
socketIO_client/parsers.py
socketIO_client/symmetries.py
socketIO_client/transports.py
socketIO_client/tests/__init__.py
socketIO_client/tests/index.html
socketIO_client/tests/package.json
socketIO_client/tests/proxy.js
socketIO_client/tests/serve.js
socketIO_client/tests/ssl.crt
socketIO_client/tests/ssl.key
socketIO_client3-0.8.0.dist-info/DESCRIPTION.rst
socketIO_client3-0.8.0.dist-info/METADATA
socketIO_client3-0.8.0.dist-info/RECORD
socketIO_client3-0.8.0.dist-info/WHEEL
socketIO_client3-0.8.0.dist-info/metadata.json
socketIO_client3-0.8.0.dist-info/top_level.txt
