Metadata-Version: 2.0
Name: socketIO-client3
Version: 0.8.0
Summary: A socket.io client library
Home-page: https://github.com/MisterWil/socketIO-client3
Author: Wil Schrader
Author-email: wilrader@gmail.com
License: MIT
Keywords: socket.io node.js
Platform: UNKNOWN
Classifier: Intended Audience :: Developers
Classifier: Programming Language :: Python
Classifier: Programming Language :: Python :: 2
Classifier: Programming Language :: Python :: 3
Classifier: License :: OSI Approved :: MIT License
Classifier: Development Status :: 5 - Production/Stable
Requires-Dist: requests (>=2.7.0)
Requires-Dist: six
Requires-Dist: websocket-client
